{
  "metadata": {
    "version": "1.0.1",
    "updated": "2025-06-03",
    "source": "EAEU Customs"
  },
  "groups": [
    {"id": "01", "name": "Живые животные"},
    {"id": "02", "name": "Мясо и пищевые мясные субпродукты"},
    {"id": "84", "name": "Ядерные реакторы, котлы, оборудование и механические устройства"},
    {"id": "85", "name": "Электрические машины и оборудование"}
  ],
  "codes": [
    {
      "code": "8471300000",
      "name": "Ноутбуки и планшеты",
      "description": "Портативные вычислительные машины массой не более 10 кг",
      "group": "84",
      "duties": {
        "base": 0,
        "china": 0,
        "eu": 0
      },
      "certification": ["ТР ТС 004", "ТР ТС 020"],
      "restrictions": []
    },
    {
      "code": "8517120000", 
      "name": "Мобильные телефоны",
      "description": "Телефонные аппараты для сотовых сетей связи",
      "group": "85",
      "duties": {
        "base": 0,
        "china": 0,
        "eu": 0
      },
      "certification": ["ТР ТС 020"],
      "restrictions": []
    },
    {
      "code": "0203290000",
      "name": "Свинина замороженная",
      "description": "Мясо свиней замороженное, туши, полутуши и отруба",
      "group": "02",
      "duties": {
        "base": 25,
        "china": 25,
        "eu": 25,
        "usa": 25
      },
      "certification": ["ТР ТС 021", "СЭС"],
      "restrictions": []
    },
    {
      "code": "0203120000",
      "name": "Свинина свежая",
      "description": "Мясо свиней свежее или охлажденное, туши и полутуши",
      "group": "02",
      "duties": {
        "base": 15,
        "china": 15,
        "eu": 15
      },
      "certification": ["ТР ТС 021", "СЭС", "Ветеринарное свидетельство"],
      "restrictions": []
    },
    {
      "code": "0901110000",
      "name": "Кофе",
      "description": "Кофе необжаренный, без кофеина",
      "group": "09",
      "duties": {
        "base": 10,
        "china": 10,
        "eu": 5
      },
      "certification": ["СЭС"],
      "restrictions": []
    },
    {
      "code": "1701140000",
      "name": "Сахар тростниковый",
      "description": "Сахар тростниковый сырец без добавления ароматизирующих или красящих веществ",
      "group": "17",
      "duties": {
        "base": 20,
        "china": 20,
        "eu": 15
      },
      "certification": ["ТР ТС 021"],
      "restrictions": []
    }
  ]
}